metricspaces/R1.py
metricspaces/__init__.py
metricspaces/cli.py
metricspaces/decorators.py
metricspaces/mds.py
metricspaces/metricspace.py
metricspaces/np_point.py
metricspaces/numpypoint.py
metricspaces/quotientspace.py
metricspaces-0.4.0.dist-info/LICENSE
metricspaces-0.4.0.dist-info/METADATA
metricspaces-0.4.0.dist-info/WHEEL
metricspaces-0.4.0.dist-info/top_level.txt
metricspaces-0.4.0.dist-info/RECORD
