Metadata-Version: 2.1
Name: metricspaces
Version: 0.4.0
Summary: A package for computing with metric spaces
Home-page: https://github.com/donsheehy/metricspaces
Author: Donald R. Sheehy
Author-email: don.r.sheehy@gmail.com
Classifier: Programming Language :: Python :: 3
Classifier: License :: OSI Approved :: MIT License
Classifier: Operating System :: OS Independent
Requires-Python: >=3.8
License-File: LICENSE
